[
    {
        "text": "Greta your first climate strike was a lonely\nevent a little over a year ago, and in the",
        "start": 10.849,
        "duration": 5.76
    },
    {
        "text": "intervening time, you have sparked the interest\nof millions literally of children around the",
        "start": 16.609,
        "duration": 4.641
    },
    {
        "text": "globe demanding action for climate change.",
        "start": 21.25,
        "duration": 4.369
    },
    {
        "text": "What's your message to world leaders today?",
        "start": 25.619,
        "duration": 10.801
    },
    {
        "text": "My message is that we'll be watching you?",
        "start": 36.42,
        "duration": 11.99
    },
    {
        "text": "This is all wrong.",
        "start": 48.41,
        "duration": 1.949
    },
    {
        "text": "I shouldn't be up here.",
        "start": 50.359,
        "duration": 3.151
    },
    {
        "text": "I should be back in school, on the other side\nof the ocean.",
        "start": 53.51,
        "duration": 4.86
    },
    {
        "text": "Yet you all come to us young people for hope.",
        "start": 58.37,
        "duration": 4.439
    },
    {
        "text": "How dare you!",
        "start": 62.809,
        "duration": 2.64
    },
    {
        "text": "You have stolen my dreams and my childhood\nwith your empty words.",
        "start": 65.449,
        "duration": 4.821
    },
    {
        "text": "And yet I'm one of the lucky ones.",
        "start": 70.27,
        "duration": 4.82
    },
    {
        "text": "People are suffering.",
        "start": 75.09,
        "duration": 1.949
    },
    {
        "text": "People are dying.",
        "start": 77.039,
        "duration": 1.811
    },
    {
        "text": "Entire ecosystems are collapsing.",
        "start": 78.85,
        "duration": 3.619
    },
    {
        "text": "We are in the beginning of a mass extinction,\nand all you can talk about is money, and fairy",
        "start": 82.469,
        "duration": 6.591
    },
    {
        "text": "tales of eternal economic growth.",
        "start": 89.06,
        "duration": 3.3
    },
    {
        "text": "How dare you!",
        "start": 92.36,
        "duration": 9.59
    },
    {
        "text": "For more than 30 years the science has been\ncrystal clear.",
        "start": 101.95,
        "duration": 5.83
    },
    {
        "text": "How dare you continue to look away, and come\nhere saying that you're doing enough when",
        "start": 107.78,
        "duration": 6.589
    },
    {
        "text": "the politics and solutions needed are still\nnowhere in sight.",
        "start": 114.369,
        "duration": 6.381
    },
    {
        "text": "You say you hear us and that you understand\nthe urgency.",
        "start": 120.75,
        "duration": 5.009
    },
    {
        "text": "But no matter how sad and angry I am, I do\nnot want to believe that.",
        "start": 125.759,
        "duration": 5.991
    },
    {
        "text": "Because if you really understood the situation\nand still kept on failing to act, then you",
        "start": 131.75,
        "duration": 6.231
    },
    {
        "text": "would be evil.",
        "start": 137.981,
        "duration": 1.419
    },
    {
        "text": "And that I refuse to believe.",
        "start": 139.4,
        "duration": 8.85
    },
    {
        "text": "The popular idea of cutting our emissions\nin half in 10 years only gives us a 50% chance",
        "start": 148.25,
        "duration": 7.3
    },
    {
        "text": "of staying below 1.5 degrees (Celsius) and\nthe risk of setting off irreversible chain",
        "start": 155.55,
        "duration": 4.75
    },
    {
        "text": "reactions beyond human control.",
        "start": 160.3,
        "duration": 3.81
    },
    {
        "text": "Fifty percent may be acceptable to you.",
        "start": 164.11,
        "duration": 4.29
    },
    {
        "text": "But those numbers do not include tipping points,\nmost feedback loops, additional warming hidden",
        "start": 168.4,
        "duration": 6.62
    },
    {
        "text": "by toxic air pollution or the aspects of equity\nand climate justice.",
        "start": 175.02,
        "duration": 4.43
    },
    {
        "text": "They also rely on my generation sucking hundreds\nof billions of tons of your CO2 out of the",
        "start": 179.45,
        "duration": 8.29
    },
    {
        "text": "air with technologies that barely exist.",
        "start": 187.74,
        "duration": 4.74
    },
    {
        "text": "So a 50% risk is simply not acceptable to\nus – we who have to live with the consequences.",
        "start": 192.48,
        "duration": 8.97
    },
    {
        "text": "To have a 67% chance of staying below a 1.5\ndegrees global temperature rise – the best",
        "start": 201.45,
        "duration": 7.06
    },
    {
        "text": "odds given by the (Intergovernmental Panel\non Climate Change) – the world had 420 gigatons",
        "start": 208.51,
        "duration": 5.36
    },
    {
        "text": "of CO2 left to emit back on Jan. 1, 2018.",
        "start": 213.87,
        "duration": 6.44
    },
    {
        "text": "Today that figure is already down to less\nthan 350 gigatons.",
        "start": 220.31,
        "duration": 5.62
    },
    {
        "text": "How dare you pretend that this can be solved\nwith just \"business as usual\" and some technical",
        "start": 225.93,
        "duration": 5.67
    },
    {
        "text": "solutions?",
        "start": 231.6,
        "duration": 2.31
    },
    {
        "text": "With today's emissions levels, that remaining\nCO2 budget will be entirely gone within less",
        "start": 233.91,
        "duration": 7.49
    },
    {
        "text": "than eight and a half years.",
        "start": 241.4,
        "duration": 4.91
    },
    {
        "text": "There will not be any solutions or plans presented\nin line with these figures here today, because",
        "start": 246.31,
        "duration": 6.621
    },
    {
        "text": "these numbers are too uncomfortable and you\nare still not mature enough to tell it like",
        "start": 252.931,
        "duration": 5.859
    },
    {
        "text": "it is.",
        "start": 258.79,
        "duration": 2.4
    },
    {
        "text": "You are failing us.",
        "start": 261.19,
        "duration": 1.349
    },
    {
        "text": "But the young people are starting to understand\nyour betrayal.",
        "start": 262.539,
        "duration": 5.931
    },
    {
        "text": "The eyes of all future generations are upon\nyou.",
        "start": 268.47,
        "duration": 3.85
    },
    {
        "text": "And if you choose to fail us, I say: We will\nnever forgive you.",
        "start": 272.32,
        "duration": 14.18
    },
    {
        "text": "We will not let you get away with this.",
        "start": 286.5,
        "duration": 2.81
    },
    {
        "text": "Right here, right now is where we draw the\nline.",
        "start": 289.31,
        "duration": 3.43
    },
    {
        "text": "The world is waking up.",
        "start": 292.74,
        "duration": 3.72
    },
    {
        "text": "And change is coming, whether you like it\nor not.",
        "start": 296.46,
        "duration": 4.04
    },
    {
        "text": "Thank you.",
        "start": 300.5,
        "duration": 0.96
    }
]