[
    {
        "text": "[Music]",
        "start": 0.0,
        "duration": 1.52
    },
    {
        "text": "homeboy we're breaking up the peach",
        "start": 0.16,
        "duration": 3.2
    },
    {
        "text": "rings you know what it's good so now we",
        "start": 1.52,
        "duration": 4.239
    },
    {
        "text": "got our yes way rose okay i'm coming up",
        "start": 3.36,
        "duration": 6.72
    },
    {
        "text": "buddy rose no wait okay all right",
        "start": 5.759,
        "duration": 4.321
    },
    {
        "text": "so now let's just get some of this in",
        "start": 10.4,
        "duration": 3.359
    },
    {
        "text": "here y'all go what is he doing is he",
        "start": 11.759,
        "duration": 3.601
    },
    {
        "text": "gonna put that in the freezer hell yeah",
        "start": 13.759,
        "duration": 4.161
    },
    {
        "text": "homeboy",
        "start": 15.36,
        "duration": 3.839
    },
    {
        "text": "now let me get this in the freezer ice",
        "start": 17.92,
        "duration": 3.68
    },
    {
        "text": "this bad boy up excuse them why put this",
        "start": 19.199,
        "duration": 4.08
    },
    {
        "text": "in here hey did you see at least the",
        "start": 21.6,
        "duration": 3.839
    },
    {
        "text": "rock i got frozen in here okay there we",
        "start": 23.279,
        "duration": 3.201
    },
    {
        "text": "go",
        "start": 25.439,
        "duration": 3.441
    },
    {
        "text": "here we go homeboy good to go now we",
        "start": 26.48,
        "duration": 4.0
    },
    {
        "text": "just let these fall in",
        "start": 28.88,
        "duration": 3.199
    },
    {
        "text": "you can smell the rose and it's",
        "start": 30.48,
        "duration": 3.36
    },
    {
        "text": "delicioso",
        "start": 32.079,
        "duration": 3.441
    },
    {
        "text": "now we're coming in and we can hit it",
        "start": 33.84,
        "duration": 3.92
    },
    {
        "text": "with some peach vodka okay the good",
        "start": 35.52,
        "duration": 3.359
    },
    {
        "text": "stuff",
        "start": 37.76,
        "duration": 5.2
    },
    {
        "text": "one two three four",
        "start": 38.879,
        "duration": 4.081
    },
    {
        "text": "so there's alcohol on alcohol",
        "start": 43.04,
        "duration": 4.16
    },
    {
        "text": "amen",
        "start": 46.16,
        "duration": 3.12
    },
    {
        "text": "come behind that now hit this with a",
        "start": 47.2,
        "duration": 3.44
    },
    {
        "text": "little",
        "start": 49.28,
        "duration": 3.2
    },
    {
        "text": "simple syrup just to sweeten her up you",
        "start": 50.64,
        "duration": 2.45
    },
    {
        "text": "know what i mean",
        "start": 52.48,
        "duration": 2.399
    },
    {
        "text": "[Music]",
        "start": 53.09,
        "duration": 5.149
    },
    {
        "text": "guys now we have here frozen peaches get",
        "start": 54.879,
        "duration": 5.041
    },
    {
        "text": "them bad boys in there frozen",
        "start": 58.239,
        "duration": 6.16
    },
    {
        "text": "strawberries get them bad boys in there",
        "start": 59.92,
        "duration": 4.479
    },
    {
        "text": "[Applause]",
        "start": 66.44,
        "duration": 2.76
    },
    {
        "text": "i want a little chance to left you know",
        "start": 67.68,
        "duration": 2.88
    },
    {
        "text": "what i mean",
        "start": 69.2,
        "duration": 3.52
    },
    {
        "text": "good to go all right brothers and",
        "start": 70.56,
        "duration": 5.36
    },
    {
        "text": "sisters watch this now",
        "start": 72.72,
        "duration": 4.48
    },
    {
        "text": "you know",
        "start": 75.92,
        "duration": 3.839
    },
    {
        "text": "get a nice little flow in there",
        "start": 77.2,
        "duration": 4.32
    },
    {
        "text": "oh lord look at it look at the gooey",
        "start": 79.759,
        "duration": 3.601
    },
    {
        "text": "goodness man",
        "start": 81.52,
        "duration": 4.56
    },
    {
        "text": "look at the gooey goodness amen amen",
        "start": 83.36,
        "duration": 5.2
    },
    {
        "text": "brothers amen look at that",
        "start": 86.08,
        "duration": 5.6
    },
    {
        "text": "come over here for part two the sequel",
        "start": 88.56,
        "duration": 4.4
    },
    {
        "text": "okay",
        "start": 91.68,
        "duration": 2.799
    },
    {
        "text": "this they say the sequel is never as",
        "start": 92.96,
        "duration": 2.72
    },
    {
        "text": "good as the original but look at",
        "start": 94.479,
        "duration": 4.0
    },
    {
        "text": "terminator terminator 2 is legit homeboy",
        "start": 95.68,
        "duration": 4.799
    },
    {
        "text": "okay now the subsequent stuff okay but",
        "start": 98.479,
        "duration": 4.32
    },
    {
        "text": "that's why i only doing two glasses okay",
        "start": 100.479,
        "duration": 3.28
    },
    {
        "text": "because when you start getting the",
        "start": 102.799,
        "duration": 2.64
    },
    {
        "text": "terminator three in four and five holy",
        "start": 103.759,
        "duration": 3.521
    },
    {
        "text": "crap now brothers and sisters you wanna",
        "start": 105.439,
        "duration": 4.0
    },
    {
        "text": "watch this okay you get some of these",
        "start": 107.28,
        "duration": 3.76
    },
    {
        "text": "little strawberries you cut off the top",
        "start": 109.439,
        "duration": 2.64
    },
    {
        "text": "like so",
        "start": 111.04,
        "duration": 2.64
    },
    {
        "text": "and then we just get some nice little",
        "start": 112.079,
        "duration": 3.601
    },
    {
        "text": "slices here oh yeah this is all about",
        "start": 113.68,
        "duration": 3.759
    },
    {
        "text": "beauty now okay this is all about",
        "start": 115.68,
        "duration": 4.32
    },
    {
        "text": "keeping it sexy and down in there",
        "start": 117.439,
        "duration": 4.401
    },
    {
        "text": "you want a gorgeous",
        "start": 120.0,
        "duration": 3.6
    },
    {
        "text": "and i find two strawberries that are",
        "start": 121.84,
        "duration": 3.52
    },
    {
        "text": "beautiful",
        "start": 123.6,
        "duration": 3.6
    },
    {
        "text": "two strawberries that have stood above",
        "start": 125.36,
        "duration": 3.36
    },
    {
        "text": "all the others you know",
        "start": 127.2,
        "duration": 4.08
    },
    {
        "text": "ones that go",
        "start": 128.72,
        "duration": 4.64
    },
    {
        "text": "gorgeous little strawberry they come",
        "start": 131.28,
        "duration": 3.52
    },
    {
        "text": "over here we need a little peach to hang",
        "start": 133.36,
        "duration": 4.4
    },
    {
        "text": "off the side now okay",
        "start": 134.8,
        "duration": 2.96
    },
    {
        "text": "eat slice come here with a little cup",
        "start": 137.84,
        "duration": 4.16
    },
    {
        "text": "maybe",
        "start": 139.92,
        "duration": 3.36
    },
    {
        "text": "oh yeah",
        "start": 142.0,
        "duration": 2.879
    },
    {
        "text": "beautiful",
        "start": 143.28,
        "duration": 3.76
    },
    {
        "text": "then guys i stick my little straw in",
        "start": 144.879,
        "duration": 5.911
    },
    {
        "text": "like so and i grab my peach rings okay",
        "start": 147.04,
        "duration": 5.199
    },
    {
        "text": "[Music]",
        "start": 150.79,
        "duration": 3.29
    },
    {
        "text": "why you always gotta put candy on it why",
        "start": 152.239,
        "duration": 3.441
    },
    {
        "text": "don't you just leave the candy off miss",
        "start": 154.08,
        "duration": 3.6
    },
    {
        "text": "miserable there's a disney movie about",
        "start": 155.68,
        "duration": 3.6
    },
    {
        "text": "you miserable",
        "start": 157.68,
        "duration": 3.36
    },
    {
        "text": "and there you have it",
        "start": 159.28,
        "duration": 4.35
    },
    {
        "text": "the peach frozee",
        "start": 161.04,
        "duration": 9.04
    },
    {
        "text": "[Music]",
        "start": 163.63,
        "duration": 8.689
    },
    {
        "text": "wow that's good oh boy sometimes i",
        "start": 170.08,
        "duration": 4.159
    },
    {
        "text": "impress myself you know like i'm telling",
        "start": 172.319,
        "duration": 3.441
    },
    {
        "text": "you and the sequel the sequel let's see",
        "start": 174.239,
        "duration": 2.441
    },
    {
        "text": "let's check the sequel",
        "start": 175.76,
        "duration": 3.6
    },
    {
        "text": "[Music]",
        "start": 176.68,
        "duration": 5.08
    },
    {
        "text": "oh damn the sequel is equally delicious",
        "start": 179.36,
        "duration": 4.56
    },
    {
        "text": "okay drink responsibly don't drink and",
        "start": 181.76,
        "duration": 4.559
    },
    {
        "text": "drive okay stay tuned see what's [ __ ]",
        "start": 183.92,
        "duration": 4.08
    },
    {
        "text": "send me my chair",
        "start": 186.319,
        "duration": 5.041
    },
    {
        "text": "right later",
        "start": 188.0,
        "duration": 3.36
    }
]