[
    {
        "text": "[Music]",
        "start": 1.13,
        "duration": 3.1
    },
    {
        "text": "well our bomb deals ndu it's been an",
        "start": 15.1,
        "duration": 4.63
    },
    {
        "text": "ugly start to the morning",
        "start": 18.47,
        "duration": 3.719
    },
    {
        "text": "Eden is resting on the sofa that she",
        "start": 19.73,
        "duration": 4.77
    },
    {
        "text": "usually does she actually slept there",
        "start": 22.189,
        "duration": 4.171
    },
    {
        "text": "for you much all night stories just in",
        "start": 24.5,
        "duration": 4.73
    },
    {
        "text": "her bed playing nicely with her toys",
        "start": 26.36,
        "duration": 7.14
    },
    {
        "text": "keeping yourself distracted mummy's",
        "start": 29.23,
        "duration": 6.13
    },
    {
        "text": "outside hanging out the laundry it's a",
        "start": 33.5,
        "duration": 5.19
    },
    {
        "text": "very homely starts quite a pleasant",
        "start": 35.36,
        "duration": 6.3
    },
    {
        "text": "temperature out today and it is actually",
        "start": 38.69,
        "duration": 6.93
    },
    {
        "text": "stories checkup day her 15 month checkup",
        "start": 41.66,
        "duration": 5.94
    },
    {
        "text": "so we're gonna be taking her to see the",
        "start": 45.62,
        "duration": 4.079
    },
    {
        "text": "nurse and the doctor today there's some",
        "start": 47.6,
        "duration": 4.619
    },
    {
        "text": "kind of job involved too so we'll get",
        "start": 49.699,
        "duration": 3.961
    },
    {
        "text": "that done it's actually getting a bit",
        "start": 52.219,
        "duration": 4.62
    },
    {
        "text": "late so I better hurry up okay time for",
        "start": 53.66,
        "duration": 4.559
    },
    {
        "text": "the appointment story",
        "start": 56.839,
        "duration": 4.5
    },
    {
        "text": "you still got half hours to spare so",
        "start": 58.219,
        "duration": 5.28
    },
    {
        "text": "we're early enough let's get you in the",
        "start": 61.339,
        "duration": 4.371
    },
    {
        "text": "car",
        "start": 63.499,
        "duration": 2.211
    },
    {
        "text": "into the health center",
        "start": 67.78,
        "duration": 3.69
    },
    {
        "text": "leaving the Motagua central the sound I",
        "start": 83.03,
        "duration": 5.64
    },
    {
        "text": "think that's how you pronounce it",
        "start": 87.09,
        "duration": 5.279
    },
    {
        "text": "okay let's get you home me it's time for",
        "start": 88.67,
        "duration": 6.129
    },
    {
        "text": "your nap so we thought the story was do",
        "start": 92.369,
        "duration": 5.82
    },
    {
        "text": "a jab today but apparently not and sesh",
        "start": 94.799,
        "duration": 7.471
    },
    {
        "text": "I had a job in space this was it yeah so",
        "start": 98.189,
        "duration": 6.36
    },
    {
        "text": "that was a bit of a surprise story is",
        "start": 102.27,
        "duration": 3.719
    },
    {
        "text": "all healthy and good",
        "start": 104.549,
        "duration": 3.6
    },
    {
        "text": "she's grown she's put on half a kilo in",
        "start": 105.989,
        "duration": 4.291
    },
    {
        "text": "weight so all on track eh",
        "start": 108.149,
        "duration": 6.45
    },
    {
        "text": "yeah it's going our dr. Leandro was",
        "start": 110.28,
        "duration": 5.879
    },
    {
        "text": "there for the first time in ages we",
        "start": 114.599,
        "duration": 3.0
    },
    {
        "text": "haven't seen him for a while cuz he's",
        "start": 116.159,
        "duration": 4.14
    },
    {
        "text": "been off and we told him for the first",
        "start": 117.599,
        "duration": 4.681
    },
    {
        "text": "time that story and us we are",
        "start": 120.299,
        "duration": 3.541
    },
    {
        "text": "vegetarians and he gave us some",
        "start": 122.28,
        "duration": 3.75
    },
    {
        "text": "guidelines that he's emailed for what",
        "start": 123.84,
        "duration": 4.02
    },
    {
        "text": "the Portuguese say you should be eating",
        "start": 126.03,
        "duration": 3.569
    },
    {
        "text": "and drinking as a child on a vegetarian",
        "start": 127.86,
        "duration": 3.45
    },
    {
        "text": "diet so it's interesting to know that",
        "start": 129.599,
        "duration": 3.811
    },
    {
        "text": "they catering for stuff like this",
        "start": 131.31,
        "duration": 3.959
    },
    {
        "text": "considering Portugal is a very meat",
        "start": 133.41,
        "duration": 4.02
    },
    {
        "text": "based country so it'd be interesting to",
        "start": 135.269,
        "duration": 4.141
    },
    {
        "text": "see what the guidelines are in Portugal",
        "start": 137.43,
        "duration": 3.63
    },
    {
        "text": "before raising a child on a vegetarian",
        "start": 139.41,
        "duration": 1.979
    },
    {
        "text": "diet",
        "start": 141.06,
        "duration": 3.0
    },
    {
        "text": "let's head home is hot in this car we've",
        "start": 141.389,
        "duration": 4.921
    },
    {
        "text": "just stopped to pick up some water from",
        "start": 144.06,
        "duration": 5.25
    },
    {
        "text": "the spring two big bottles that should",
        "start": 146.31,
        "duration": 5.37
    },
    {
        "text": "last us a while we used to be at this",
        "start": 149.31,
        "duration": 4.44
    },
    {
        "text": "spring so often drinking into the water",
        "start": 151.68,
        "duration": 3.149
    },
    {
        "text": "from here but then we bought these",
        "start": 153.75,
        "duration": 2.549
    },
    {
        "text": "bottoms that have got filters in them",
        "start": 154.829,
        "duration": 3.091
    },
    {
        "text": "and then we didn't need to get it so",
        "start": 156.299,
        "duration": 5.06
    },
    {
        "text": "much we Bailey over here now",
        "start": 157.92,
        "duration": 3.439
    },
    {
        "text": "we've just arrived home and story has",
        "start": 163.17,
        "duration": 4.63
    },
    {
        "text": "gone to sleep so I'm gonna have to leave",
        "start": 165.94,
        "duration": 3.9
    },
    {
        "text": "her in the car I think don't wake her up",
        "start": 167.8,
        "duration": 3.23
    },
    {
        "text": "his cruel",
        "start": 169.84,
        "duration": 10.47
    },
    {
        "text": "Satan stories sleeping alone leave her",
        "start": 171.03,
        "duration": 13.75
    },
    {
        "text": "alone she's sleeping Hey she's sleeping",
        "start": 180.31,
        "duration": 14.43
    },
    {
        "text": "oh my goodness eat them what a crazy",
        "start": 184.78,
        "duration": 12.51
    },
    {
        "text": "thing she is sometimes I wonder if she's",
        "start": 194.74,
        "duration": 4.08
    },
    {
        "text": "actually a real dog he doesn't really",
        "start": 197.29,
        "duration": 4.11
    },
    {
        "text": "like doing any dog face looks like it's",
        "start": 198.82,
        "duration": 3.87
    },
    {
        "text": "straight back in the house straight back",
        "start": 201.4,
        "duration": 3.06
    },
    {
        "text": "in the car",
        "start": 202.69,
        "duration": 4.5
    },
    {
        "text": "this is today's ball of health my lunch",
        "start": 204.46,
        "duration": 6.18
    },
    {
        "text": "looking good I've got some tabular not",
        "start": 207.19,
        "duration": 4.74
    },
    {
        "text": "sure how you say that we just bought",
        "start": 210.64,
        "duration": 1.86
    },
    {
        "text": "that from Lidl",
        "start": 211.93,
        "duration": 3.35
    },
    {
        "text": "some white beans isn't rocket lovely",
        "start": 212.5,
        "duration": 5.46
    },
    {
        "text": "laundry is still drying in the Sun it's",
        "start": 215.28,
        "duration": 4.99
    },
    {
        "text": "lovely and warm out here this is what it",
        "start": 217.96,
        "duration": 4.68
    },
    {
        "text": "looks like this is our view for the day",
        "start": 220.27,
        "duration": 5.22
    },
    {
        "text": "and we have a temperature of 22 degrees",
        "start": 222.64,
        "duration": 5.25
    },
    {
        "text": "again we got an email from one of our",
        "start": 225.49,
        "duration": 4.23
    },
    {
        "text": "viewers the other day who is suggesting",
        "start": 227.89,
        "duration": 3.93
    },
    {
        "text": "that we put the month at the beginning",
        "start": 229.72,
        "duration": 4.98
    },
    {
        "text": "of every video we make to help viewers",
        "start": 231.82,
        "duration": 4.98
    },
    {
        "text": "who are in America or Canada or",
        "start": 234.7,
        "duration": 4.77
    },
    {
        "text": "somewhere else to gauge what the",
        "start": 236.8,
        "duration": 5.04
    },
    {
        "text": "temperature is at what time yeah it",
        "start": 239.47,
        "duration": 4.14
    },
    {
        "text": "might be quite a good idea something to",
        "start": 241.84,
        "duration": 3.149
    },
    {
        "text": "think about just a little bit more",
        "start": 243.61,
        "duration": 4.79
    },
    {
        "text": "information it's s the pudding the month",
        "start": 244.989,
        "duration": 6.481
    },
    {
        "text": "or saying what month it is like per",
        "start": 248.4,
        "duration": 4.87
    },
    {
        "text": "video so if you just tuned in for the",
        "start": 251.47,
        "duration": 3.81
    },
    {
        "text": "first time you're like oh that's what",
        "start": 253.27,
        "duration": 3.3
    },
    {
        "text": "it's like in February",
        "start": 255.28,
        "duration": 4.829
    },
    {
        "text": "it's very by the way somebody else",
        "start": 256.57,
        "duration": 4.919
    },
    {
        "text": "suggested that we should say what the",
        "start": 260.109,
        "duration": 3.121
    },
    {
        "text": "Fahrenheit is as well but we use the",
        "start": 261.489,
        "duration": 6.601
    },
    {
        "text": "metric system here yourself I guess with",
        "start": 263.23,
        "duration": 6.66
    },
    {
        "text": "months you won't know what it is unless",
        "start": 268.09,
        "duration": 4.02
    },
    {
        "text": "we say but with temperatures you can",
        "start": 269.89,
        "duration": 3.87
    },
    {
        "text": "just google it well there England's a",
        "start": 272.11,
        "duration": 3.09
    },
    {
        "text": "bit of funny isn't it sash because in",
        "start": 273.76,
        "duration": 4.17
    },
    {
        "text": "the UK we use miles but we also use the",
        "start": 275.2,
        "duration": 3.48
    },
    {
        "text": "metric system",
        "start": 277.93,
        "duration": 3.35
    },
    {
        "text": "we're blended aren't we it's weird",
        "start": 278.68,
        "duration": 5.489
    },
    {
        "text": "talking about doing miles we were having",
        "start": 281.28,
        "duration": 4.45
    },
    {
        "text": "more and more chats about the whole van",
        "start": 284.169,
        "duration": 3.421
    },
    {
        "text": "life situation and we've been getting",
        "start": 285.73,
        "duration": 4.08
    },
    {
        "text": "quite a lot of emails and support from",
        "start": 287.59,
        "duration": 3.81
    },
    {
        "text": "different people giving us their advice",
        "start": 289.81,
        "duration": 4.37
    },
    {
        "text": "and their resources on",
        "start": 291.4,
        "duration": 4.25
    },
    {
        "text": "how to do research for this type of",
        "start": 294.18,
        "duration": 3.87
    },
    {
        "text": "lifestyle and the other day we were",
        "start": 295.65,
        "duration": 6.75
    },
    {
        "text": "watching a video about caravans and now",
        "start": 298.05,
        "duration": 6.51
    },
    {
        "text": "we're thinking that a caravan would",
        "start": 302.4,
        "duration": 4.049
    },
    {
        "text": "actually be more suitable for us and our",
        "start": 304.56,
        "duration": 3.57
    },
    {
        "text": "lifestyle than an actual Motorhome",
        "start": 306.449,
        "duration": 4.321
    },
    {
        "text": "simply because you get more space it is",
        "start": 308.13,
        "duration": 4.17
    },
    {
        "text": "something that we would need to look",
        "start": 310.77,
        "duration": 3.72
    },
    {
        "text": "into in a lot more depth because it's a",
        "start": 312.3,
        "duration": 5.58
    },
    {
        "text": "whole new world of things that you would",
        "start": 314.49,
        "duration": 5.37
    },
    {
        "text": "need to kind of take into account",
        "start": 317.88,
        "duration": 5.069
    },
    {
        "text": "believe it or not for about 16,000",
        "start": 319.86,
        "duration": 5.04
    },
    {
        "text": "pounds which is less than a deposit on a",
        "start": 322.949,
        "duration": 4.681
    },
    {
        "text": "house in most countries you can get an",
        "start": 324.9,
        "duration": 6.15
    },
    {
        "text": "amazing 20 foot long house basically",
        "start": 327.63,
        "duration": 4.98
    },
    {
        "text": "that you could live in whether we would",
        "start": 331.05,
        "duration": 2.82
    },
    {
        "text": "actually be able to live in that space",
        "start": 332.61,
        "duration": 4.08
    },
    {
        "text": "or not I still don't know but it's",
        "start": 333.87,
        "duration": 5.549
    },
    {
        "text": "definitely piqued my interest Jane I do",
        "start": 336.69,
        "duration": 5.069
    },
    {
        "text": "have rather conflicting views on the",
        "start": 339.419,
        "duration": 5.581
    },
    {
        "text": "whole Caravan buying situation I was",
        "start": 341.759,
        "duration": 6.72
    },
    {
        "text": "looking up vintage retro campers and",
        "start": 345.0,
        "duration": 5.43
    },
    {
        "text": "little touring campers that you hook up",
        "start": 348.479,
        "duration": 3.961
    },
    {
        "text": "to your car they are much smaller",
        "start": 350.43,
        "duration": 3.54
    },
    {
        "text": "obviously but they look so much better",
        "start": 352.44,
        "duration": 6.39
    },
    {
        "text": "and they call us this is a perfect",
        "start": 353.97,
        "duration": 6.479
    },
    {
        "text": "example of how our relationship works",
        "start": 358.83,
        "duration": 4.14
    },
    {
        "text": "there is the dreamer and I'm the realist",
        "start": 360.449,
        "duration": 4.5
    },
    {
        "text": "there is no way we would be able to live",
        "start": 362.97,
        "duration": 9.18
    },
    {
        "text": "in a vintage 1970s tiny little box or it",
        "start": 364.949,
        "duration": 8.881
    },
    {
        "text": "depends on your situation it depends on",
        "start": 372.15,
        "duration": 4.199
    },
    {
        "text": "your goals yeah but also it gives you",
        "start": 373.83,
        "duration": 5.28
    },
    {
        "text": "some freedom to travel and I think that",
        "start": 376.349,
        "duration": 5.581
    },
    {
        "text": "especially with a dog and a baby we're",
        "start": 379.11,
        "duration": 4.2
    },
    {
        "text": "not going to be able to do any of that",
        "start": 381.93,
        "duration": 3.54
    },
    {
        "text": "in a little thing having one of these",
        "start": 383.31,
        "duration": 3.72
    },
    {
        "text": "little vintage caravans would be an",
        "start": 385.47,
        "duration": 3.449
    },
    {
        "text": "addition to our life like if we were to",
        "start": 387.03,
        "duration": 3.81
    },
    {
        "text": "buy a house and have that on the land",
        "start": 388.919,
        "duration": 3.78
    },
    {
        "text": "and go for a little camping trip but",
        "start": 390.84,
        "duration": 4.049
    },
    {
        "text": "having a big Caravan we could actually",
        "start": 392.699,
        "duration": 4.621
    },
    {
        "text": "go longer termini I think it's like",
        "start": 394.889,
        "duration": 3.75
    },
    {
        "text": "having a rowing boat or having a big",
        "start": 397.32,
        "duration": 2.849
    },
    {
        "text": "sailboat obviously you can do more in",
        "start": 398.639,
        "duration": 3.511
    },
    {
        "text": "the big sailboat but it's not as cool as",
        "start": 400.169,
        "duration": 6.321
    },
    {
        "text": "having a little cute thing on Lake is it",
        "start": 402.15,
        "duration": 4.34
    },
    {
        "text": "yes a half the size and it didn't have",
        "start": 407.449,
        "duration": 13.06
    },
    {
        "text": "any of the resources inside it what",
        "start": 409.979,
        "duration": 12.271
    },
    {
        "text": "would be interesting for us to do is to",
        "start": 420.509,
        "duration": 3.72
    },
    {
        "text": "go to one of those caravan shows and",
        "start": 422.25,
        "duration": 4.08
    },
    {
        "text": "actually walk into them and sit in one",
        "start": 424.229,
        "duration": 2.581
    },
    {
        "text": "of them",
        "start": 426.33,
        "duration": 1.65
    },
    {
        "text": "so we actually",
        "start": 426.81,
        "duration": 4.14
    },
    {
        "text": "feel the pain of having such a small",
        "start": 427.98,
        "duration": 6.86
    },
    {
        "text": "space and see if we could live like that",
        "start": 430.95,
        "duration": 3.89
    },
    {
        "text": "it would be less than a year it would be",
        "start": 435.75,
        "duration": 4.14
    },
    {
        "text": "less than a year definitely it would be",
        "start": 437.7,
        "duration": 4.47
    },
    {
        "text": "it would be a means for us to travel",
        "start": 439.89,
        "duration": 3.9
    },
    {
        "text": "like we said before so that we could",
        "start": 442.17,
        "duration": 4.47
    },
    {
        "text": "find our place and buy a home problem",
        "start": 443.79,
        "duration": 4.02
    },
    {
        "text": "being obviously right now",
        "start": 446.64,
        "duration": 3.03
    },
    {
        "text": "we can't afford to buy a house but we",
        "start": 447.81,
        "duration": 3.72
    },
    {
        "text": "may be able to afford to buy something",
        "start": 449.67,
        "duration": 3.72
    },
    {
        "text": "like a caravan but we'll see",
        "start": 451.53,
        "duration": 4.08
    },
    {
        "text": "it's lots to think about as we've said",
        "start": 453.39,
        "duration": 4.95
    },
    {
        "text": "many times now why do you think about",
        "start": 455.61,
        "duration": 11.51
    },
    {
        "text": "all of this Aiden dog Wow",
        "start": 458.34,
        "duration": 8.78
    },
    {
        "text": "little baby come on little one",
        "start": 467.33,
        "duration": 16.32
    },
    {
        "text": "daddy you're out guess what we're doing",
        "start": 473.51,
        "duration": 15.28
    },
    {
        "text": "we're looking at caravans yeah",
        "start": 483.65,
        "duration": 9.64
    },
    {
        "text": "have there been no the caravan world",
        "start": 488.79,
        "duration": 6.9
    },
    {
        "text": "does look much geekier than the van life",
        "start": 493.29,
        "duration": 6.66
    },
    {
        "text": "world when you look at the websites as",
        "start": 495.69,
        "duration": 6.57
    },
    {
        "text": "though they have to do some research but",
        "start": 499.95,
        "duration": 4.86
    },
    {
        "text": "we found some cool stuff yeah well we",
        "start": 502.26,
        "duration": 6.15
    },
    {
        "text": "think it's cool maybe we can make it",
        "start": 504.81,
        "duration": 7.23
    },
    {
        "text": "cool can you do it three can you make it",
        "start": 508.41,
        "duration": 9.509
    },
    {
        "text": "cool maybe there's some caravans in",
        "start": 512.04,
        "duration": 20.19
    },
    {
        "text": "Betty this is the unicorn quarry hey",
        "start": 517.919,
        "duration": 16.711
    },
    {
        "text": "Stewie you finished your lunch and what",
        "start": 532.23,
        "duration": 4.47
    },
    {
        "text": "did the nurse say to you today she said",
        "start": 534.63,
        "duration": 3.99
    },
    {
        "text": "you should try drawing with a piece of",
        "start": 536.7,
        "duration": 5.16
    },
    {
        "text": "paper and pen yeah I'll put this out for",
        "start": 538.62,
        "duration": 3.57
    },
    {
        "text": "you",
        "start": 541.86,
        "duration": 3.03
    },
    {
        "text": "it's history time you know try doing",
        "start": 542.19,
        "duration": 5.07
    },
    {
        "text": "some drawings on it oh she's already",
        "start": 544.89,
        "duration": 4.79
    },
    {
        "text": "does it really trying to draw no Fane",
        "start": 547.26,
        "duration": 6.21
    },
    {
        "text": "yeah and on the table I'll guess it's",
        "start": 549.68,
        "duration": 5.68
    },
    {
        "text": "your table",
        "start": 553.47,
        "duration": 6.359
    },
    {
        "text": "I see stories first drawing hey I'm just",
        "start": 555.36,
        "duration": 11.18
    },
    {
        "text": "gonna throw in the wood instead sharing",
        "start": 559.829,
        "duration": 17.13
    },
    {
        "text": "murdering the paper a bad start whenever",
        "start": 566.54,
        "duration": 12.07
    },
    {
        "text": "we come back from the doctor in the",
        "start": 576.959,
        "duration": 3.63
    },
    {
        "text": "nurse visits I always like to do my own",
        "start": 578.61,
        "duration": 5.759
    },
    {
        "text": "research as well on what they've said in",
        "start": 580.589,
        "duration": 6.21
    },
    {
        "text": "the second year of life the growth slows",
        "start": 584.369,
        "duration": 6.84
    },
    {
        "text": "down a lot and the child may only put on",
        "start": 586.799,
        "duration": 6.75
    },
    {
        "text": "up to 2 kilos in the second year which",
        "start": 591.209,
        "duration": 3.511
    },
    {
        "text": "is like 5 pounds",
        "start": 593.549,
        "duration": 3.72
    },
    {
        "text": "it's over see the first year of life",
        "start": 594.72,
        "duration": 5.01
    },
    {
        "text": "they're growing dramatically and story",
        "start": 597.269,
        "duration": 4.23
    },
    {
        "text": "was eight and a half kilos at her",
        "start": 599.73,
        "duration": 4.62
    },
    {
        "text": "one-year checkup so to only grow another",
        "start": 601.499,
        "duration": 5.64
    },
    {
        "text": "two kilos in a whole year it's a very",
        "start": 604.35,
        "duration": 5.669
    },
    {
        "text": "big difference she has put on 500 grams",
        "start": 607.139,
        "duration": 5.43
    },
    {
        "text": "since her year check and now story",
        "start": 610.019,
        "duration": 4.021
    },
    {
        "text": "doesn't have to go back to see the",
        "start": 612.569,
        "duration": 4.44
    },
    {
        "text": "doctor until her 18 month check now so",
        "start": 614.04,
        "duration": 6.959
    },
    {
        "text": "not until springtime tasty biscuit story",
        "start": 617.009,
        "duration": 6.93
    },
    {
        "text": "- added a biscuit and some leaves to her",
        "start": 620.999,
        "duration": 6.111
    },
    {
        "text": "artwork of the day yeah we also had a",
        "start": 623.939,
        "duration": 6.45
    },
    {
        "text": "dick and a rock I also think she's a",
        "start": 627.11,
        "duration": 8.639
    },
    {
        "text": "mixed-media artist organic material 3d",
        "start": 630.389,
        "duration": 21.51
    },
    {
        "text": "give me some dip hello you're in it's a",
        "start": 635.749,
        "duration": 19.21
    },
    {
        "text": "run I'm an old dog I don't write family",
        "start": 651.899,
        "duration": 6.09
    },
    {
        "text": "the pain your sister no we I don't do",
        "start": 654.959,
        "duration": 5.61
    },
    {
        "text": "that one tomorrow look at my miserable",
        "start": 657.989,
        "duration": 3.651
    },
    {
        "text": "face",
        "start": 660.569,
        "duration": 5.491
    },
    {
        "text": "[Laughter]",
        "start": 661.64,
        "duration": 4.42
    },
    {
        "text": "well the neighbors up two-story big",
        "start": 667.19,
        "duration": 9.9
    },
    {
        "text": "orange tractor yeah what's he doing out",
        "start": 671.63,
        "duration": 9.93
    },
    {
        "text": "there making the farm all new so they",
        "start": 677.09,
        "duration": 8.99
    },
    {
        "text": "can grow more things it's an interesting",
        "start": 681.56,
        "duration": 9.83
    },
    {
        "text": "turning around for another run yeah",
        "start": 686.08,
        "duration": 7.57
    },
    {
        "text": "that's just gonna distract story with a",
        "start": 691.39,
        "duration": 3.7
    },
    {
        "text": "little bit of reading while I get a",
        "start": 693.65,
        "duration": 3.45
    },
    {
        "text": "thumbnail made for the latest vlog while",
        "start": 695.09,
        "duration": 3.77
    },
    {
        "text": "I'm here let me show you one of the",
        "start": 697.1,
        "duration": 5.16
    },
    {
        "text": "caravans that sasha is looking at here",
        "start": 698.86,
        "duration": 3.97
    },
    {
        "text": "we go",
        "start": 702.26,
        "duration": 3.84
    },
    {
        "text": "these tiny little bent each 1970s a",
        "start": 702.83,
        "duration": 8.25
    },
    {
        "text": "straw care of hats meanwhile I was",
        "start": 706.1,
        "duration": 6.33
    },
    {
        "text": "suggesting something a little bit more",
        "start": 711.08,
        "duration": 2.1
    },
    {
        "text": "like this",
        "start": 712.43,
        "duration": 2.94
    },
    {
        "text": "I mean for about 25 grand you can get",
        "start": 713.18,
        "duration": 6.66
    },
    {
        "text": "this big old boy a little bit more space",
        "start": 715.37,
        "duration": 9.45
    },
    {
        "text": "in something like that all the",
        "start": 719.84,
        "duration": 7.08
    },
    {
        "text": "advertising is geared up towards much",
        "start": 724.82,
        "duration": 4.44
    },
    {
        "text": "older couples than we are and without",
        "start": 726.92,
        "duration": 8.31
    },
    {
        "text": "kids as well so I don't know there's",
        "start": 729.26,
        "duration": 8.13
    },
    {
        "text": "definitely appeal there but I just don't",
        "start": 735.23,
        "duration": 4.8
    },
    {
        "text": "know on the plus side in these videos",
        "start": 737.39,
        "duration": 5.01
    },
    {
        "text": "they do show lots of doggy life with",
        "start": 740.03,
        "duration": 8.01
    },
    {
        "text": "them sorry Eden will be fine it's dinner",
        "start": 742.4,
        "duration": 8.64
    },
    {
        "text": "time for somebody and we're sharing the",
        "start": 748.04,
        "duration": 11.16
    },
    {
        "text": "same dinner tonight aren't we and what",
        "start": 751.04,
        "duration": 11.16
    },
    {
        "text": "is dog gonna hmm well the Morgan out for",
        "start": 759.2,
        "duration": 3.35
    },
    {
        "text": "dinner",
        "start": 762.2,
        "duration": 5.16
    },
    {
        "text": "biscuits and meat look outside look at",
        "start": 762.55,
        "duration": 8.05
    },
    {
        "text": "that blue sky lots of sheep action going",
        "start": 767.36,
        "duration": 6.0
    },
    {
        "text": "on over there someone's fire burning",
        "start": 770.6,
        "duration": 4.88
    },
    {
        "text": "already",
        "start": 773.36,
        "duration": 2.12
    },
    {
        "text": "the local life going on here more tracks",
        "start": 775.68,
        "duration": 6.21
    },
    {
        "text": "is all just normal day-to-day life here",
        "start": 778.56,
        "duration": 5.25
    },
    {
        "text": "going on in central Portugal we are",
        "start": 781.89,
        "duration": 3.51
    },
    {
        "text": "going to continue discussing whether we",
        "start": 783.81,
        "duration": 4.29
    },
    {
        "text": "should buy a caravan or not and see if",
        "start": 785.4,
        "duration": 4.11
    },
    {
        "text": "that fits into the next stage of our",
        "start": 788.1,
        "duration": 3.3
    },
    {
        "text": "life I'm also gonna in the video for",
        "start": 789.51,
        "duration": 3.78
    },
    {
        "text": "today if you don't know we are vlogging",
        "start": 791.4,
        "duration": 4.53
    },
    {
        "text": "six days a week so if you want to see",
        "start": 793.29,
        "duration": 4.2
    },
    {
        "text": "the weekend vlogs you can become a",
        "start": 795.93,
        "duration": 3.93
    },
    {
        "text": "patron by clicking the link up here we",
        "start": 797.49,
        "duration": 4.8
    },
    {
        "text": "also put up sneak-peek videos and",
        "start": 799.86,
        "duration": 4.65
    },
    {
        "text": "pictures on there and little bits and",
        "start": 802.29,
        "duration": 4.32
    },
    {
        "text": "pieces from the rest of the day when we",
        "start": 804.51,
        "duration": 3.54
    },
    {
        "text": "turn off the camera so if you're",
        "start": 806.61,
        "duration": 3.36
    },
    {
        "text": "interested in any of that that link or",
        "start": 808.05,
        "duration": 3.75
    },
    {
        "text": "in the description below and we'll see",
        "start": 809.97,
        "duration": 4.94
    },
    {
        "text": "you next time bye",
        "start": 811.8,
        "duration": 3.11
    },
    {
        "text": "[Music]",
        "start": 814.98,
        "duration": 3.11
    }
]